{
  "meetups": [
    {
      "name": "DC iOS",
      "url": "https://www.meetup.com/DC-iOS",
      "logoUrl": "dc-ios.jpg"
    },
    {
      "name": "DC Android",
      "url": "https://www.meetup.com/DCAndroid/",
      "logoUrl": "dc-android.jpg"
    },
    {
      "name": "DC Flutter",
      "url": "https://www.meetup.com/DCFlutter/",
      "logoUrl": "dc-flutter.jpg"
    },
    {
      "name": "DC Kotlin",
      "url": "https://www.meetup.com/DCKotlin/",
      "logoUrl": "dc-kotlin.jpg"
    },
    {
      "name": "GDG DC",
      "url": "https://www.meetup.com/gdg-dc/",
      "logoUrl": "gdg-dc.png"
    }
  ]
}